rtl/alu_top.v
`timescale 1ns/1ps

module alu_top(

    input  [7:0] A,
    input  [7:0] B,
    input  [2:0] opcode,

    output reg [7:0] result,
    output reg carry,
    output reg zero,
    output reg overflow

);

reg [8:0] temp;

always @(*) begin

    carry = 0;
    overflow = 0;

    case(opcode)

        3'b000: begin
            temp = A + B;
            result = temp[7:0];
            carry = temp[8];
        end

        3'b001: begin
            temp = A - B;
            result = temp[7:0];
            carry = temp[8];
        end

        3'b010:
            result = A & B;

        3'b011:
            result = A | B;

        3'b100:
            result = A ^ B;

        3'b101:
            result = ~A;

        3'b110:
            result = A << 1;

        3'b111:
            result = A >> 1;

    endcase

    if(result == 8'b00000000)
        zero = 1;
    else
        zero = 0;

end

endmodule

tb/alu_tb.v
`timescale 1ns/1ps

module alu_tb;

reg [7:0] A;
reg [7:0] B;
reg [2:0] opcode;

wire [7:0] result;
wire carry;
wire zero;
wire overflow;

alu_top uut (

    .A(A),
    .B(B),
    .opcode(opcode),

    .result(result),
    .carry(carry),
    .zero(zero),
    .overflow(overflow)

);

initial begin

    $dumpfile("waveform.vcd");
    $dumpvars(0,alu_tb);

    // ADD
    A = 15;
    B = 10;
    opcode = 3'b000;
    #10;

    // SUB
    A = 20;
    B = 5;
    opcode = 3'b001;
    #10;

    // AND
    A = 15;
    B = 3;
    opcode = 3'b010;
    #10;

    // OR
    A = 15;
    B = 3;
    opcode = 3'b011;
    #10;

    // XOR
    A = 15;
    B = 3;
    opcode = 3'b100;
    #10;

    // NOT
    A = 15;
    B = 0;
    opcode = 3'b101;
    #10;

    // SHIFT LEFT
    A = 15;
    opcode = 3'b110;
    #10;

    // SHIFT RIGHT
    A = 15;
    opcode = 3'b111;
    #10;

    $finish;

end

endmodule

simulation/waveform.vcd
$date
	Mon Jun 15 20:27:58 2026
$end
$version
	Icarus Verilog
$end
$timescale
	1ps
$end
$scope module alu_tb $end
$var wire 1 ! zero $end
$var wire 8 " result [7:0] $end
$var wire 1 # overflow $end
$var wire 1 $ carry $end
$var reg 8 % A [7:0] $end
$var reg 8 & B [7:0] $end
$var reg 3 ' opcode [2:0] $end
$scope module uut $end
$var wire 8 ( A [7:0] $end
$var wire 8 ) B [7:0] $end
$var wire 3 * opcode [2:0] $end
$var reg 1 $ carry $end
$var reg 1 # overflow $end
$var reg 8 + result [7:0] $end
$var reg 9 , temp [8:0] $end
$var reg 1 ! zero $end
$upscope $end
$upscope $end
$enddefinitions $end
#0
$dumpvars
b11001 ,
b11001 +
b0 *
b1010 )
b1111 (
b0 '
b1010 &
b1111 %
0$
0#
b11001 "
0!
$end
#10000
b1111 "
b1111 +
b1111 ,
b1 '
b1 *
b101 &
b101 )
b10100 %
b10100 (
#20000
b11 "
b11 +
b10 '
b10 *
b11 &
b11 )
b1111 %
b1111 (
#30000
b1111 "
b1111 +
b11 '
b11 *
#40000
b1100 "
b1100 +
b100 '
b100 *
#50000
b11110000 "
b11110000 +
b101 '
b101 *
b0 &
b0 )
#60000
b11110 "
b11110 +
b110 '
b110 *
#70000
b111 "
b111 +
b111 '
b111 *
